genpy/__init__.py
genpy/base.py
genpy/dynamic.py
genpy/generate_initpy.py
genpy/generate_numpy.py
genpy/generate_struct.py
genpy/generator.py
genpy/genpy_main.py
genpy/message.py
genpy/rostime.py
genpy/genmsg/__init__.py
genpy/genmsg/base.py
genpy/genmsg/command_line.py
genpy/genmsg/deps.py
genpy/genmsg/gentools.py
genpy/genmsg/msg_loader.py
genpy/genmsg/msgs.py
genpy/genmsg/names.py
genpy/genmsg/srvs.py
genpy/genmsg/template_tools.py
rosbag/__init__.py
rosbag/bag.py
rosbag_standalone-1.17.4.1.dist-info/licenses/LICENSE
rosbag_standalone-1.17.4.1.dist-info/METADATA
rosbag_standalone-1.17.4.1.dist-info/WHEEL
rosbag_standalone-1.17.4.1.dist-info/top_level.txt
rosbag_standalone-1.17.4.1.dist-info/RECORD
