Metadata-Version: 2.4
Name: rosbag-standalone
Version: 1.17.4.1
Summary: A standalone version of the ROS1 rosbag library - Python package for reading and writing ROS1 bag files
Author: Willow Garage, ROS Community
Maintainer-email: Martin Valgur <martin.valgur@gmail.com>
License-Expression: BSD-3-Clause
Project-URL: Homepage, https://github.com/valgur/rosbag-standalone
Project-URL: Documentation, https://wiki.ros.org/rosbag
Keywords: ros,ros1,rosbag,robotics
Classifier: Programming Language :: Python :: 3
Classifier: Operating System :: OS Independent
Requires-Python: >=3.7
License-File: LICENSE
Requires-Dist: PyYAML
Requires-Dist: lz4
Dynamic: license-file
